{"lastUsed":1524761867450,"path":"C:\/Users\/aaron\/eclipse\/kurs1618\/workspace","projectCount":3,"recentFiles":[{"path":"\/Kapitel 2\/src\/adhoc7","parentWorkspace":"C:\/Users\/aaron\/eclipse\/kurs1618\/workspace","name":"ObjContTest.java","lastModified":1524660704899,"locationURI":"file:\/C:\/Users\/aaron\/eclipse\/kurs1618\/workspace\/Kapitel%202\/src\/adhoc7\/ObjContTest.java"},{"path":"\/Kapitel 2\/src\/adhoc8","parentWorkspace":"C:\/Users\/aaron\/eclipse\/kurs1618\/workspace","name":"NumberContainerWithMaximum.java","lastModified":1524663640175,"locationURI":"file:\/C:\/Users\/aaron\/eclipse\/kurs1618\/workspace\/Kapitel%202\/src\/adhoc8\/NumberContainerWithMaximum.java"},{"path":"\/Kapitel 2\/src\/EA2","parentWorkspace":"C:\/Users\/aaron\/eclipse\/kurs1618\/workspace","name":"Aufgabe 1","lastModified":1524730021689,"locationURI":"file:\/C:\/Users\/aaron\/eclipse\/kurs1618\/workspace\/Kapitel%202\/src\/EA2\/Aufgabe%201"},{"path":"\/Kapitel 2\/src\/EA2","parentWorkspace":"C:\/Users\/aaron\/eclipse\/kurs1618\/workspace","name":"BinaryNode.java","lastModified":1524749536237,"locationURI":"file:\/C:\/Users\/aaron\/eclipse\/kurs1618\/workspace\/Kapitel%202\/src\/EA2\/BinaryNode.java"},{"path":"\/Kapitel 2\/src\/EA2","parentWorkspace":"C:\/Users\/aaron\/eclipse\/kurs1618\/workspace","name":"RingpufferTest.java","lastModified":1524761806071,"locationURI":"file:\/C:\/Users\/aaron\/eclipse\/kurs1618\/workspace\/Kapitel%202\/src\/EA2\/RingpufferTest.java"},{"path":"\/Kapitel 2\/src\/EA2","parentWorkspace":"C:\/Users\/aaron\/eclipse\/kurs1618\/workspace","name":"Car.java","lastModified":1524749955653,"locationURI":"file:\/C:\/Users\/aaron\/eclipse\/kurs1618\/workspace\/Kapitel%202\/src\/EA2\/Car.java"},{"path":"\/Kapitel 2\/src\/adhoc3","parentWorkspace":"C:\/Users\/aaron\/eclipse\/kurs1618\/workspace","name":"utilArrays.java"},{"path":"\/Kapitel 2\/src\/adhoc2","parentWorkspace":"C:\/Users\/aaron\/eclipse\/kurs1618\/workspace","name":"TestFraction.java"},{"path":"\/Kapitel 2\/src\/adhoc4","parentWorkspace":"C:\/Users\/aaron\/eclipse\/kurs1618\/workspace","name":"ToyTest.java","lastModified":1524557144983},{"path":"\/Kapitel 2\/src\/EA2","parentWorkspace":"C:\/Users\/aaron\/eclipse\/kurs1618\/workspace","name":"CarTest.java","lastModified":1524750679610,"locationURI":"file:\/C:\/Users\/aaron\/eclipse\/kurs1618\/workspace\/Kapitel%202\/src\/EA2\/CarTest.java"},{"path":"\/Kapitel 2\/src\/adhoc9","parentWorkspace":"C:\/Users\/aaron\/eclipse\/kurs1618\/workspace","name":"WeighableObjects.java","lastModified":1524665499738,"locationURI":"file:\/C:\/Users\/aaron\/eclipse\/kurs1618\/workspace\/Kapitel%202\/src\/adhoc9\/WeighableObjects.java"},{"path":"\/Kapitel 2\/src\/SA1","parentWorkspace":"C:\/Users\/aaron\/eclipse\/kurs1618\/workspace","name":"Person.java","lastModified":1524722546773,"locationURI":"file:\/C:\/Users\/aaron\/eclipse\/kurs1618\/workspace\/Kapitel%202\/src\/SA1\/Person.java"},{"path":"\/Kapitel 2\/src\/adhoc2","parentWorkspace":"C:\/Users\/aaron\/eclipse\/kurs1618\/workspace","name":"Fraction.java"},{"path":"\/Kapitel 1\/src\/de\/adhoc\/selbsttest1","parentWorkspace":"C:\/Users\/aaron\/eclipse\/kurs1618\/workspace","name":"Sortieren.java"},{"path":"\/Kapitel 2\/src\/SA4","parentWorkspace":"C:\/Users\/aaron\/eclipse\/kurs1618\/workspace","name":"Tree.java","lastModified":1524726499447,"locationURI":"file:\/C:\/Users\/aaron\/eclipse\/kurs1618\/workspace\/Kapitel%202\/src\/SA4\/Tree.java"},{"path":"\/Kapitel 1\/src\/de\/adhoc\/kap1","parentWorkspace":"C:\/Users\/aaron\/eclipse\/kurs1618\/workspace","name":"AddressBuch.java"},{"path":"\/Kapitel 2\/src\/adhoc9","parentWorkspace":"C:\/Users\/aaron\/eclipse\/kurs1618\/workspace","name":"MaxWeightContainer.java","lastModified":1524665362060,"locationURI":"file:\/C:\/Users\/aaron\/eclipse\/kurs1618\/workspace\/Kapitel%202\/src\/adhoc9\/MaxWeightContainer.java"},{"path":"\/Kapitel 1\/src\/de\/adhoc\/kap1","parentWorkspace":"C:\/Users\/aaron\/eclipse\/kurs1618\/workspace","name":"Person.java","lastModified":1524659964849},{"path":"\/Kapitel 2\/src\/adhoc7","parentWorkspace":"C:\/Users\/aaron\/eclipse\/kurs1618\/workspace","name":"Person.java","lastModified":1524660297031,"locationURI":"file:\/C:\/Users\/aaron\/eclipse\/kurs1618\/workspace\/Kapitel%202\/src\/adhoc7\/Person.java"},{"path":"\/Kapitel 2\/src\/EA2","parentWorkspace":"C:\/Users\/aaron\/eclipse\/kurs1618\/workspace","name":"TestTree.java","lastModified":1524749364427,"locationURI":"file:\/C:\/Users\/aaron\/eclipse\/kurs1618\/workspace\/Kapitel%202\/src\/EA2\/TestTree.java"},{"path":"\/Kapitel 2\/src\/adhoc9","parentWorkspace":"C:\/Users\/aaron\/eclipse\/kurs1618\/workspace","name":"MaxWeightContainerTest.java","lastModified":1524665499910,"locationURI":"file:\/C:\/Users\/aaron\/eclipse\/kurs1618\/workspace\/Kapitel%202\/src\/adhoc9\/MaxWeightContainerTest.java"},{"path":"\/Kapitel 2\/src\/adhoc5","parentWorkspace":"C:\/Users\/aaron\/eclipse\/kurs1618\/workspace","name":"LinkedList1618.java","lastModified":1524659703620,"locationURI":"file:\/C:\/Users\/aaron\/eclipse\/kurs1618\/workspace\/Kapitel%202\/src\/adhoc5\/LinkedList1618.java"},{"path":"\/Kapitel 1\/src\/EA1","parentWorkspace":"C:\/Users\/aaron\/eclipse\/kurs1618\/workspace","name":"GameOfLife.java"},{"path":"\/Kapitel 2\/src\/SA2","parentWorkspace":"C:\/Users\/aaron\/eclipse\/kurs1618\/workspace","name":"Wochentag.java","lastModified":1524725231786,"locationURI":"file:\/C:\/Users\/aaron\/eclipse\/kurs1618\/workspace\/Kapitel%202\/src\/SA2\/Wochentag.java"},{"path":"\/Kapitel 2\/src\/SA2","parentWorkspace":"C:\/Users\/aaron\/eclipse\/kurs1618\/workspace","name":"KeinTagException.java","lastModified":1524724818393,"locationURI":"file:\/C:\/Users\/aaron\/eclipse\/kurs1618\/workspace\/Kapitel%202\/src\/SA2\/KeinTagException.java"},{"path":"\/Kapitel 2\/src\/EA2","parentWorkspace":"C:\/Users\/aaron\/eclipse\/kurs1618\/workspace","name":"Foo.java","lastModified":1524730124796,"locationURI":"file:\/C:\/Users\/aaron\/eclipse\/kurs1618\/workspace\/Kapitel%202\/src\/EA2\/Foo.java"},{"path":"\/Kapitel 2\/src\/EA2","parentWorkspace":"C:\/Users\/aaron\/eclipse\/kurs1618\/workspace","name":"RealCar.java","lastModified":1524749951289,"locationURI":"file:\/C:\/Users\/aaron\/eclipse\/kurs1618\/workspace\/Kapitel%202\/src\/EA2\/RealCar.java"},{"path":"\/Kapitel 2\/src\/SA1","parentWorkspace":"C:\/Users\/aaron\/eclipse\/kurs1618\/workspace","name":"Cat.java","lastModified":1524722546773,"locationURI":"file:\/C:\/Users\/aaron\/eclipse\/kurs1618\/workspace\/Kapitel%202\/src\/SA1\/Cat.java"},{"path":"\/Kapitel 2\/src\/SA1","parentWorkspace":"C:\/Users\/aaron\/eclipse\/kurs1618\/workspace","name":"Printable.java","lastModified":1524722550306,"locationURI":"file:\/C:\/Users\/aaron\/eclipse\/kurs1618\/workspace\/Kapitel%202\/src\/SA1\/Printable.java"},{"path":"\/Kapitel 1\/src\/EA1","parentWorkspace":"C:\/Users\/aaron\/eclipse\/kurs1618\/workspace","name":"gauss.java"},{"path":"\/Kapitel 2\/src\/adhoc5","parentWorkspace":"C:\/Users\/aaron\/eclipse\/kurs1618\/workspace","name":"LinkedList1618Test.java","lastModified":1524636115742,"locationURI":"file:\/C:\/Users\/aaron\/eclipse\/kurs1618\/workspace\/Kapitel%202\/src\/adhoc5\/LinkedList1618Test.java"},{"path":"\/Kapitel 2\/src\/SA1","parentWorkspace":"C:\/Users\/aaron\/eclipse\/kurs1618\/workspace","name":"PrintableListTest.java","lastModified":1524724039005,"locationURI":"file:\/C:\/Users\/aaron\/eclipse\/kurs1618\/workspace\/Kapitel%202\/src\/SA1\/PrintableListTest.java"},{"path":"\/Kapitel 2\/src\/EA2","parentWorkspace":"C:\/Users\/aaron\/eclipse\/kurs1618\/workspace","name":"CarFactory.java","lastModified":1524749981255,"locationURI":"file:\/C:\/Users\/aaron\/eclipse\/kurs1618\/workspace\/Kapitel%202\/src\/EA2\/CarFactory.java"},{"path":"\/Kapitel 2\/src\/adhoc8","parentWorkspace":"C:\/Users\/aaron\/eclipse\/kurs1618\/workspace","name":"NumberContainer.java","lastModified":1524663709866,"locationURI":"file:\/C:\/Users\/aaron\/eclipse\/kurs1618\/workspace\/Kapitel%202\/src\/adhoc8\/NumberContainer.java"},{"path":"\/Kapitel 1\/src\/de\/adhoc\/selbsttest1","parentWorkspace":"C:\/Users\/aaron\/eclipse\/kurs1618\/workspace","name":"StrToInt.java"},{"path":"\/Kapitel 2\/src\/adhoc9","parentWorkspace":"C:\/Users\/aaron\/eclipse\/kurs1618\/workspace","name":"Weighable.java","lastModified":1524664741666,"locationURI":"file:\/C:\/Users\/aaron\/eclipse\/kurs1618\/workspace\/Kapitel%202\/src\/adhoc9\/Weighable.java"},{"path":"\/Kapitel 2\/src\/SA1","parentWorkspace":"C:\/Users\/aaron\/eclipse\/kurs1618\/workspace","name":"Book.java","lastModified":1524722546773,"locationURI":"file:\/C:\/Users\/aaron\/eclipse\/kurs1618\/workspace\/Kapitel%202\/src\/SA1\/Book.java"},{"path":"\/Kapitel 2\/src\/adhoc4","parentWorkspace":"C:\/Users\/aaron\/eclipse\/kurs1618\/workspace","name":"ToyFactory.java"},{"path":"\/Kapitel 2\/src\/adhoc4","parentWorkspace":"C:\/Users\/aaron\/eclipse\/kurs1618\/workspace","name":"Toy.java"},{"path":"\/Kapitel 2\/src\/EA2","parentWorkspace":"C:\/Users\/aaron\/eclipse\/kurs1618\/workspace","name":"Ringpuffer.java","lastModified":1524753843433,"locationURI":"file:\/C:\/Users\/aaron\/eclipse\/kurs1618\/workspace\/Kapitel%202\/src\/EA2\/Ringpuffer.java"},{"path":"\/Kapitel 2\/src\/adhoc7","parentWorkspace":"C:\/Users\/aaron\/eclipse\/kurs1618\/workspace","name":"ObjectContainer.java","lastModified":1524660085047,"locationURI":"file:\/C:\/Users\/aaron\/eclipse\/kurs1618\/workspace\/Kapitel%202\/src\/adhoc7\/ObjectContainer.java"},{"path":"\/Kapitel 2\/src\/SA1","parentWorkspace":"C:\/Users\/aaron\/eclipse\/kurs1618\/workspace","name":"PrintableList.java","lastModified":1524729800538,"locationURI":"file:\/C:\/Users\/aaron\/eclipse\/kurs1618\/workspace\/Kapitel%202\/src\/SA1\/PrintableList.java"},{"path":"\/Kapitel 2\/src\/SA2","parentWorkspace":"C:\/Users\/aaron\/eclipse\/kurs1618\/workspace","name":"WochentagTest.java","lastModified":1524725572843,"locationURI":"file:\/C:\/Users\/aaron\/eclipse\/kurs1618\/workspace\/Kapitel%202\/src\/SA2\/WochentagTest.java"}]}